AllSkyCam4OLEODL/__init__.py
AllSkyCam4OLEODL/api.py
AllSkyCam4OLEODL/constants.py
AllSkyCam4OLEODL/gui.py
AllSkyCam4OLEODL/image_processing.py
AllSkyCam4OLEODL/input_checks.py
AllSkyCam4OLEODL/link_budget.py
AllSkyCam4OLEODL/printer.py
allskycam4oleodl-0.4.0.dist-info/LICENSE.txt
allskycam4oleodl-0.4.0.dist-info/METADATA
allskycam4oleodl-0.4.0.dist-info/WHEEL
allskycam4oleodl-0.4.0.dist-info/RECORD
