Metadata-Version: 2.1
Name: allskycam4oleodl
Version: 0.4.0
Summary: Tracking software for OLEODL using Allied Vision cameras. Developed alongside DLR-OP-IKN.
Home-page: https://github.com/Ikerald/AllSkyCam4OLEODL
License: MIT
Keywords: OLEODL,AllSky
Author: Iker Aldasoro
Author-email: ikeraldasorot@gmail.com
Requires-Python: >=3.7,<4.0
Classifier: License :: OSI Approved :: MIT License
Classifier: Programming Language :: Python :: 3
Classifier: Programming Language :: Python :: 3.7
Classifier: Programming Language :: Python :: 3.8
Classifier: Programming Language :: Python :: 3.9
Classifier: Programming Language :: Python :: 3.10
Classifier: Programming Language :: Python :: 3.11
Classifier: Programming Language :: Python :: 3.12
Requires-Dist: matplotlib (>=3.5.3,<4.0.0)
Requires-Dist: mplcursors (>=0.5.1,<0.6.0)
Requires-Dist: numpy (>=1.21.6,<2.0.0)
Requires-Dist: opencv-python (>=4.5.5.64,<5.0.0.0)
Requires-Dist: pytz (>=2021.3,<2022.0)
Requires-Dist: scipy (>=1.7.3,<2.0.0)
Requires-Dist: tk
Project-URL: Repository, https://github.com/Ikerald/AllSkyCam4OLEODL
